naro/__init__.py
naro/module1.py
naro/module2.py
naro-0.0.3.dist-info/LICENSE
naro-0.0.3.dist-info/METADATA
naro-0.0.3.dist-info/WHEEL
naro-0.0.3.dist-info/top_level.txt
naro-0.0.3.dist-info/RECORD
